pandajedi/__init__.py
pandajedi/jedibrokerage/AtlasAnalJobBroker.py
pandajedi/jedibrokerage/AtlasBrokerUtils.py
pandajedi/jedibrokerage/AtlasProdJobBroker.py
pandajedi/jedibrokerage/AtlasProdTaskBroker.py
pandajedi/jedibrokerage/GenJobBroker.py
pandajedi/jedibrokerage/JobBrokerBase.py
pandajedi/jedibrokerage/TaskBrokerBase.py
pandajedi/jedibrokerage/__init__.py
pandajedi/jediconfig/__init__.py
pandajedi/jediconfig/jedi_config.py
pandajedi/jedicore/FactoryBase.py
pandajedi/jedicore/InputChunk.py
pandajedi/jedicore/Interaction.py
pandajedi/jedicore/JediCacheSpec.py
pandajedi/jedicore/JediCoreUtils.py
pandajedi/jedicore/JediDBProxy.py
pandajedi/jedicore/JediDBProxyPool.py
pandajedi/jedicore/JediDBSchemaInfo.py
pandajedi/jedicore/JediDatasetSpec.py
pandajedi/jedicore/JediException.py
pandajedi/jedicore/JediFileSpec.py
pandajedi/jedicore/JediPatch.py
pandajedi/jedicore/JediTaskBuffer.py
pandajedi/jedicore/JediTaskBufferInterface.py
pandajedi/jedicore/JediTaskSpec.py
pandajedi/jedicore/MsgWrapper.py
pandajedi/jedicore/ParseJobXML.py
pandajedi/jedicore/ProcessUtils.py
pandajedi/jedicore/SiteCandidate.py
pandajedi/jedicore/ThreadUtils.py
pandajedi/jedicore/WorkQueue.py
pandajedi/jedicore/WorkQueueMapper.py
pandajedi/jedicore/__init__.py
pandajedi/jediddm/AtlasDDMClient.py
pandajedi/jediddm/DDMClientBase.py
pandajedi/jediddm/DDMInterface.py
pandajedi/jediddm/GenDDMClient.py
pandajedi/jediddm/__init__.py
pandajedi/jedidog/AtlasAnalWatchDog.py
pandajedi/jedidog/AtlasDataLocalityUpdaterWatchDog.py
pandajedi/jedidog/AtlasProdWatchDog.py
pandajedi/jedidog/AtlasQueueFillerWatchDog.py
pandajedi/jedidog/AtlasTaskWithholderWatchDog.py
pandajedi/jedidog/GenWatchDog.py
pandajedi/jedidog/JumboWatchDog.py
pandajedi/jedidog/TypicalWatchDogBase.py
pandajedi/jedidog/WatchDogBase.py
pandajedi/jedidog/__init__.py
pandajedi/jediexec/reniceJEDI.py
pandajedi/jedigen/AtlasTaskGenerator.py
pandajedi/jedigen/TaskGeneratorBase.py
pandajedi/jedigen/__init__.py
pandajedi/jedimsgprocessor/__init__.py
panda_jedi-0.2.0.dist-info/LICENSE.txt
panda_jedi-0.2.0.dist-info/METADATA
panda_jedi-0.2.0.dist-info/WHEEL
panda_jedi-0.2.0.dist-info/top_level.txt
panda_jedi-0.2.0.dist-info/RECORD
