Metadata-Version: 2.1
Name: panda-jedi
Version: 0.2.0
Summary: JEDI Package
Home-page: https://twiki.cern.ch/twiki/bin/view/Atlas/PanDA
Author: Panda Team
Author-email: atlas-adc-panda@cern.ch
License: GPL
License-File: LICENSE.txt
Requires-Dist: six
Requires-Dist: panda-common >=0.0.43
Requires-Dist: panda-server >=0.0.37
Requires-Dist: python-daemon
Requires-Dist: numpy
Requires-Dist: pyyaml
Requires-Dist: requests
Requires-Dist: packaging
Provides-Extra: atlasprod
Requires-Dist: cx-Oracle ; extra == 'atlasprod'
Requires-Dist: rucio-clients ; extra == 'atlasprod'
Requires-Dist: idds-common ; extra == 'atlasprod'
Requires-Dist: idds-client ; extra == 'atlasprod'
Provides-Extra: mysql
Requires-Dist: mysqlclient ; extra == 'mysql'
Provides-Extra: oracle
Requires-Dist: cx-Oracle ; extra == 'oracle'
Provides-Extra: postgres
Requires-Dist: psycopg2-binary ; extra == 'postgres'
Provides-Extra: rucio
Requires-Dist: rucio-clients ; extra == 'rucio'
